twig/__init__.py
twig/compiler.py
twig/filesystem.py
twig/backends/__init__.py
twig/backends/vyper.py
twig/utils/__init__.py
twig/utils/compiler.py
twig-0.1.0a5.dist-info/LICENSE
twig-0.1.0a5.dist-info/METADATA
twig-0.1.0a5.dist-info/WHEEL
twig-0.1.0a5.dist-info/top_level.txt
twig-0.1.0a5.dist-info/RECORD
