Metadata-Version: 2.1
Name: twig
Version: 0.1.0a5
Summary: twig: A tool for Ethereum smart contract development.
Home-page: https://github.com/ethereum/twig
Author: Nick Gheorghita
Author-email: nickg@ethereum.org
License: MIT
Keywords: ethereum
Platform: UNKNOWN
Classifier: Development Status :: 2 - Pre-Alpha
Classifier: Intended Audience :: Developers
Classifier: License :: OSI Approved :: MIT License
Classifier: Natural Language :: English
Classifier: Programming Language :: Python :: 3
Classifier: Programming Language :: Python :: 3.6
Requires-Python: >=3.6, <4
Requires-Dist: eth-utils (<2,>=1)
Requires-Dist: eth-typing (<2,>=1)
Requires-Dist: ethpm (<1,>=0.1.4a7)
Requires-Dist: pytest-ethereum (<1,>=0.1.3a1)
Requires-Dist: web3[tester] (<5,>=4.7)
Requires-Dist: vyper (<1,>=0.1.0b5)
Provides-Extra: dev
Requires-Dist: bumpversion (<1,>=0.5.3) ; extra == 'dev'
Requires-Dist: pytest-watch (<5,>=4.1.0) ; extra == 'dev'
Requires-Dist: wheel ; extra == 'dev'
Requires-Dist: twine ; extra == 'dev'
Requires-Dist: ipython ; extra == 'dev'
Requires-Dist: pytest (==3.3.2) ; extra == 'dev'
Requires-Dist: pytest-xdist ; extra == 'dev'
Requires-Dist: tox (<3,>=2.9.1) ; extra == 'dev'
Requires-Dist: black (<19,>=18.6b4) ; extra == 'dev'
Requires-Dist: flake8 (==3.4.1) ; extra == 'dev'
Requires-Dist: isort (<5,>=4.2.15) ; extra == 'dev'
Requires-Dist: mypy (<0.600) ; extra == 'dev'
Requires-Dist: Sphinx (<2,>=1.6.5) ; extra == 'dev'
Requires-Dist: sphinx-rtd-theme (>=0.1.9) ; extra == 'dev'
Provides-Extra: doc
Requires-Dist: Sphinx (<2,>=1.6.5) ; extra == 'doc'
Requires-Dist: sphinx-rtd-theme (>=0.1.9) ; extra == 'doc'
Provides-Extra: lint
Requires-Dist: black (<19,>=18.6b4) ; extra == 'lint'
Requires-Dist: flake8 (==3.4.1) ; extra == 'lint'
Requires-Dist: isort (<5,>=4.2.15) ; extra == 'lint'
Requires-Dist: mypy (<0.600) ; extra == 'lint'
Provides-Extra: test
Requires-Dist: pytest (==3.3.2) ; extra == 'test'
Requires-Dist: pytest-xdist ; extra == 'test'
Requires-Dist: tox (<3,>=2.9.1) ; extra == 'test'
